[
    {
        "publicada": 1,
        "numero": 9118,
        "escrutado": true,
        "digitalizado": 1,
        "id_informacion_mesa_corporacion": "0107019020179118",
        "nombre_archivo": "https://elecciones-hnd-publicacion-prod-us-east-1.s3.us-east-1.amazonaws.com/ACTAS/07/0719091180041000.pdf?X-Amz-Algorithm=AWS4-HMAC-SHA256&X-Amz-Credential=AKIATNSYFO5EYDYMH46K%2F20251207%2Fus-east-1%2Fs3%2Faws4_request&X-Amz-Date=20251207T131701Z&X-Amz-Expires=7200&X-Amz-SignedHeaders=host&X-Amz-Signature=7e1c5e2e152474cee6f6647b38172d660bc81a2b21e037d01ae6113f707f0c6c",
        "etiquetas": [
            "Divulgada Correctamente",
            "Pendiente de Revisi\u00f3n"
        ]
    },
    {
        "publicada": 1,
        "numero": 9119,
        "escrutado": true,
        "digitalizado": 1,
        "id_informacion_mesa_corporacion": "0107019020179119",
        "nombre_archivo": "https://elecciones-hnd-publicacion-prod-us-east-1.s3.us-east-1.amazonaws.com/ACTAS/07/0719091190041000.pdf?X-Amz-Algorithm=AWS4-HMAC-SHA256&X-Amz-Credential=AKIATNSYFO5EYDYMH46K%2F20251207%2Fus-east-1%2Fs3%2Faws4_request&X-Amz-Date=20251207T131701Z&X-Amz-Expires=7200&X-Amz-SignedHeaders=host&X-Amz-Signature=69578adf147248f3529d2265f1e307e4b987798db5ac6d5d61c1e011fc9edb98",
        "etiquetas": [
            "Divulgada Correctamente",
            "Pendiente de Revisi\u00f3n"
        ]
    },
    {
        "publicada": 1,
        "numero": 9120,
        "escrutado": true,
        "digitalizado": 1,
        "id_informacion_mesa_corporacion": "0107019020179120",
        "nombre_archivo": "https://elecciones-hnd-publicacion-prod-us-east-1.s3.us-east-1.amazonaws.com/ACTAS/07/0719091200041000.pdf?X-Amz-Algorithm=AWS4-HMAC-SHA256&X-Amz-Credential=AKIATNSYFO5EYDYMH46K%2F20251207%2Fus-east-1%2Fs3%2Faws4_request&X-Amz-Date=20251207T131701Z&X-Amz-Expires=7200&X-Amz-SignedHeaders=host&X-Amz-Signature=713c9b2ffbc917e452e1381183f04a6684260e2a370e36a3b136eb339e96d309",
        "etiquetas": [
            "Inconsistencia",
            "Pendiente de Revisi\u00f3n"
        ]
    }
]