[
    {
        "publicada": 1,
        "numero": 5160,
        "escrutado": true,
        "digitalizado": 1,
        "id_informacion_mesa_corporacion": "0105002010015160",
        "nombre_archivo": "https://elecciones-hnd-publicacion-prod-us-east-1.s3.us-east-1.amazonaws.com/E14/05/002/01/001/E14_P01_05_002_001_00_001_5160_1954.pdf?X-Amz-Algorithm=AWS4-HMAC-SHA256&X-Amz-Credential=AKIATNSYFO5EYDYMH46K%2F20251207%2Fus-east-1%2Fs3%2Faws4_request&X-Amz-Date=20251207T120641Z&X-Amz-Expires=7200&X-Amz-SignedHeaders=host&X-Amz-Signature=f888556533ef548635f8ba7c66e79e1f60a58b506b24ef82f3b36232e33f0d08",
        "etiquetas": [
            "Divulgada Correctamente"
        ]
    },
    {
        "publicada": 1,
        "numero": 5161,
        "escrutado": true,
        "digitalizado": 1,
        "id_informacion_mesa_corporacion": "0105002010015161",
        "nombre_archivo": "https://elecciones-hnd-publicacion-prod-us-east-1.s3.us-east-1.amazonaws.com/E14/05/002/01/001/E14_P01_05_002_001_00_001_5161_1954.pdf?X-Amz-Algorithm=AWS4-HMAC-SHA256&X-Amz-Credential=AKIATNSYFO5EYDYMH46K%2F20251207%2Fus-east-1%2Fs3%2Faws4_request&X-Amz-Date=20251207T120641Z&X-Amz-Expires=7200&X-Amz-SignedHeaders=host&X-Amz-Signature=83c3c1ce8c1f3481a313430546851b4080966ba24359b38a3a8d8aa64c3c753e",
        "etiquetas": [
            "Divulgada Correctamente"
        ]
    },
    {
        "publicada": 1,
        "numero": 5162,
        "escrutado": true,
        "digitalizado": 1,
        "id_informacion_mesa_corporacion": "0105002010015162",
        "nombre_archivo": "https://elecciones-hnd-publicacion-prod-us-east-1.s3.us-east-1.amazonaws.com/E14/05/002/01/001/E14_P01_05_002_001_00_001_5162_1954.pdf?X-Amz-Algorithm=AWS4-HMAC-SHA256&X-Amz-Credential=AKIATNSYFO5EYDYMH46K%2F20251207%2Fus-east-1%2Fs3%2Faws4_request&X-Amz-Date=20251207T120641Z&X-Amz-Expires=7200&X-Amz-SignedHeaders=host&X-Amz-Signature=c45141434a260210e6fdf0db39344bee746227e4da220f8488b9cbb39f60f7a6",
        "etiquetas": [
            "Divulgada Correctamente"
        ]
    },
    {
        "publicada": 1,
        "numero": 5163,
        "escrutado": true,
        "digitalizado": 1,
        "id_informacion_mesa_corporacion": "0105002010015163",
        "nombre_archivo": "https://elecciones-hnd-publicacion-prod-us-east-1.s3.us-east-1.amazonaws.com/E14/05/002/01/001/E14_P01_05_002_001_00_001_5163_1954.pdf?X-Amz-Algorithm=AWS4-HMAC-SHA256&X-Amz-Credential=AKIATNSYFO5EYDYMH46K%2F20251207%2Fus-east-1%2Fs3%2Faws4_request&X-Amz-Date=20251207T120641Z&X-Amz-Expires=7200&X-Amz-SignedHeaders=host&X-Amz-Signature=909e2087ed7a8f4784c4e44536eb5c6740e8aea1bedc814cf4c0d620a1a03e04",
        "etiquetas": [
            "Divulgada Correctamente"
        ]
    },
    {
        "publicada": 1,
        "numero": 5164,
        "escrutado": true,
        "digitalizado": 1,
        "id_informacion_mesa_corporacion": "0105002010015164",
        "nombre_archivo": "https://elecciones-hnd-publicacion-prod-us-east-1.s3.us-east-1.amazonaws.com/E14/05/002/01/001/E14_P01_05_002_001_00_001_5164_1955.pdf?X-Amz-Algorithm=AWS4-HMAC-SHA256&X-Amz-Credential=AKIATNSYFO5EYDYMH46K%2F20251207%2Fus-east-1%2Fs3%2Faws4_request&X-Amz-Date=20251207T120641Z&X-Amz-Expires=7200&X-Amz-SignedHeaders=host&X-Amz-Signature=6d8c010f2b772fbf36b1b6eebec2b42c4fab6c8f1bdcb9be48d3b64fa5826b1c",
        "etiquetas": [
            "Divulgada Correctamente"
        ]
    },
    {
        "publicada": 1,
        "numero": 5165,
        "escrutado": true,
        "digitalizado": 1,
        "id_informacion_mesa_corporacion": "0105002010015165",
        "nombre_archivo": "https://elecciones-hnd-publicacion-prod-us-east-1.s3.us-east-1.amazonaws.com/E14/05/002/01/001/E14_P01_05_002_001_00_001_5165_1955.pdf?X-Amz-Algorithm=AWS4-HMAC-SHA256&X-Amz-Credential=AKIATNSYFO5EYDYMH46K%2F20251207%2Fus-east-1%2Fs3%2Faws4_request&X-Amz-Date=20251207T120641Z&X-Amz-Expires=7200&X-Amz-SignedHeaders=host&X-Amz-Signature=644a36afad4514a1dafe4c32a2cec078a673e21b9f7f686f12ee8b1b36c7056a",
        "etiquetas": [
            "Divulgada Correctamente"
        ]
    },
    {
        "publicada": 1,
        "numero": 5166,
        "escrutado": true,
        "digitalizado": 1,
        "id_informacion_mesa_corporacion": "0105002010015166",
        "nombre_archivo": "https://elecciones-hnd-publicacion-prod-us-east-1.s3.us-east-1.amazonaws.com/E14/05/002/01/001/E14_P01_05_002_001_00_001_5166_1955.pdf?X-Amz-Algorithm=AWS4-HMAC-SHA256&X-Amz-Credential=AKIATNSYFO5EYDYMH46K%2F20251207%2Fus-east-1%2Fs3%2Faws4_request&X-Amz-Date=20251207T120641Z&X-Amz-Expires=7200&X-Amz-SignedHeaders=host&X-Amz-Signature=175d342efbdf5c2589097f01240acc7494cfd3a6757d4ffa4d83ac203374f2fc",
        "etiquetas": [
            "Inconsistencia"
        ]
    },
    {
        "publicada": 1,
        "numero": 5167,
        "escrutado": true,
        "digitalizado": 1,
        "id_informacion_mesa_corporacion": "0105002010015167",
        "nombre_archivo": "https://elecciones-hnd-publicacion-prod-us-east-1.s3.us-east-1.amazonaws.com/E14/05/002/01/001/E14_P01_05_002_001_00_001_5167_1955.pdf?X-Amz-Algorithm=AWS4-HMAC-SHA256&X-Amz-Credential=AKIATNSYFO5EYDYMH46K%2F20251207%2Fus-east-1%2Fs3%2Faws4_request&X-Amz-Date=20251207T120641Z&X-Amz-Expires=7200&X-Amz-SignedHeaders=host&X-Amz-Signature=b0f81f69c685b07f20bca24f718d40f19fc88fa186e3d0362f78a623fe06ebab",
        "etiquetas": [
            "Divulgada Correctamente"
        ]
    },
    {
        "publicada": 1,
        "numero": 5168,
        "escrutado": true,
        "digitalizado": 1,
        "id_informacion_mesa_corporacion": "0105002010015168",
        "nombre_archivo": "https://elecciones-hnd-publicacion-prod-us-east-1.s3.us-east-1.amazonaws.com/E14/05/002/01/001/E14_P01_05_002_001_00_001_5168_1956.pdf?X-Amz-Algorithm=AWS4-HMAC-SHA256&X-Amz-Credential=AKIATNSYFO5EYDYMH46K%2F20251207%2Fus-east-1%2Fs3%2Faws4_request&X-Amz-Date=20251207T120641Z&X-Amz-Expires=7200&X-Amz-SignedHeaders=host&X-Amz-Signature=eedb3f0c9569dff3f8b3713343ff2545cc06b350b8cc231d30a31a63b39554c8",
        "etiquetas": [
            "Inconsistencia"
        ]
    },
    {
        "publicada": 1,
        "numero": 5169,
        "escrutado": true,
        "digitalizado": 1,
        "id_informacion_mesa_corporacion": "0105002010015169",
        "nombre_archivo": "https://elecciones-hnd-publicacion-prod-us-east-1.s3.us-east-1.amazonaws.com/E14/05/002/01/001/E14_P01_05_002_001_00_001_5169_1956.pdf?X-Amz-Algorithm=AWS4-HMAC-SHA256&X-Amz-Credential=AKIATNSYFO5EYDYMH46K%2F20251207%2Fus-east-1%2Fs3%2Faws4_request&X-Amz-Date=20251207T120641Z&X-Amz-Expires=7200&X-Amz-SignedHeaders=host&X-Amz-Signature=01296321132a5b069f78be528fc4b21f0489a383266c1ce7cb939edf3703b9ca",
        "etiquetas": [
            "Divulgada Correctamente"
        ]
    },
    {
        "publicada": 1,
        "numero": 5170,
        "escrutado": true,
        "digitalizado": 1,
        "id_informacion_mesa_corporacion": "0105002010015170",
        "nombre_archivo": "https://elecciones-hnd-publicacion-prod-us-east-1.s3.us-east-1.amazonaws.com/ACTAS/05/0502051700041000.pdf?X-Amz-Algorithm=AWS4-HMAC-SHA256&X-Amz-Credential=AKIATNSYFO5EYDYMH46K%2F20251207%2Fus-east-1%2Fs3%2Faws4_request&X-Amz-Date=20251207T120641Z&X-Amz-Expires=7200&X-Amz-SignedHeaders=host&X-Amz-Signature=e8a41315c463c257dea6951698120220789919b059e6211942e669151f7d5779",
        "etiquetas": [
            "Divulgada Correctamente"
        ]
    }
]