[
    {
        "publicada": 0,
        "numero": 9838,
        "escrutado": false,
        "digitalizado": 1,
        "id_informacion_mesa_corporacion": "0108001011619838",
        "nombre_archivo": "https://elecciones-hnd-publicacion-prod-us-east-1.s3.us-east-1.amazonaws.com/E14/08/001/01/161/E14_P01_08_001_001_00_161_9838_3648.pdf?X-Amz-Algorithm=AWS4-HMAC-SHA256&X-Amz-Credential=AKIATNSYFO5EYDYMH46K%2F20251207%2Fus-east-1%2Fs3%2Faws4_request&X-Amz-Date=20251207T133528Z&X-Amz-Expires=7200&X-Amz-SignedHeaders=host&X-Amz-Signature=0c9f3c9e5fac8c249cf0895ff2e017aa348ce93c48991096dee293946c4eaff6",
        "etiquetas": [
            "Pendiente de transmisi\u00f3n"
        ]
    },
    {
        "publicada": 0,
        "numero": 9839,
        "escrutado": false,
        "digitalizado": 1,
        "id_informacion_mesa_corporacion": "0108001011619839",
        "nombre_archivo": "https://elecciones-hnd-publicacion-prod-us-east-1.s3.us-east-1.amazonaws.com/E14/08/001/01/161/E14_P01_08_001_001_00_161_9839_3648.pdf?X-Amz-Algorithm=AWS4-HMAC-SHA256&X-Amz-Credential=AKIATNSYFO5EYDYMH46K%2F20251207%2Fus-east-1%2Fs3%2Faws4_request&X-Amz-Date=20251207T133528Z&X-Amz-Expires=7200&X-Amz-SignedHeaders=host&X-Amz-Signature=72ecb0f5f8dd4a498804cb7e0dd19e1a336bf401ba799706ea390921ba724cf2",
        "etiquetas": [
            "Pendiente de transmisi\u00f3n"
        ]
    },
    {
        "publicada": 1,
        "numero": 9840,
        "escrutado": true,
        "digitalizado": 1,
        "id_informacion_mesa_corporacion": "0108001011619840",
        "nombre_archivo": "https://elecciones-hnd-publicacion-prod-us-east-1.s3.us-east-1.amazonaws.com/ACTAS/08/0801098400041000.pdf?X-Amz-Algorithm=AWS4-HMAC-SHA256&X-Amz-Credential=AKIATNSYFO5EYDYMH46K%2F20251207%2Fus-east-1%2Fs3%2Faws4_request&X-Amz-Date=20251207T133528Z&X-Amz-Expires=7200&X-Amz-SignedHeaders=host&X-Amz-Signature=31f056b00f76eef18725f430d21646d4bbd9203f3b581b5423be9490857bdfbe",
        "etiquetas": [
            "Divulgada Correctamente"
        ]
    },
    {
        "publicada": 1,
        "numero": 9841,
        "escrutado": true,
        "digitalizado": 1,
        "id_informacion_mesa_corporacion": "0108001011619841",
        "nombre_archivo": "https://elecciones-hnd-publicacion-prod-us-east-1.s3.us-east-1.amazonaws.com/ACTAS/08/0801098410041000.pdf?X-Amz-Algorithm=AWS4-HMAC-SHA256&X-Amz-Credential=AKIATNSYFO5EYDYMH46K%2F20251207%2Fus-east-1%2Fs3%2Faws4_request&X-Amz-Date=20251207T133528Z&X-Amz-Expires=7200&X-Amz-SignedHeaders=host&X-Amz-Signature=de328928e13406cd9c2510ce2cd24430bc705a8372ec7bd9b14fcc4802c204e6",
        "etiquetas": [
            "Divulgada Correctamente"
        ]
    },
    {
        "publicada": 1,
        "numero": 9842,
        "escrutado": true,
        "digitalizado": 1,
        "id_informacion_mesa_corporacion": "0108001011619842",
        "nombre_archivo": "https://elecciones-hnd-publicacion-prod-us-east-1.s3.us-east-1.amazonaws.com/E14/08/001/01/161/E14_P01_08_001_001_00_161_9842_3649.pdf?X-Amz-Algorithm=AWS4-HMAC-SHA256&X-Amz-Credential=AKIATNSYFO5EYDYMH46K%2F20251207%2Fus-east-1%2Fs3%2Faws4_request&X-Amz-Date=20251207T133528Z&X-Amz-Expires=7200&X-Amz-SignedHeaders=host&X-Amz-Signature=ad539a2c1d1de8eda3a5668e7f2ce8ec1023b51df94655752da8726f4564ae1d",
        "etiquetas": [
            "Divulgada Correctamente"
        ]
    },
    {
        "publicada": 1,
        "numero": 9843,
        "escrutado": true,
        "digitalizado": 1,
        "id_informacion_mesa_corporacion": "0108001011619843",
        "nombre_archivo": "https://elecciones-hnd-publicacion-prod-us-east-1.s3.us-east-1.amazonaws.com/E14/08/001/01/161/E14_P01_08_001_001_00_161_9843_3649.pdf?X-Amz-Algorithm=AWS4-HMAC-SHA256&X-Amz-Credential=AKIATNSYFO5EYDYMH46K%2F20251207%2Fus-east-1%2Fs3%2Faws4_request&X-Amz-Date=20251207T133528Z&X-Amz-Expires=7200&X-Amz-SignedHeaders=host&X-Amz-Signature=1d9a14581472e6839cb6d0581c6a01f52d4475621038cc67406653662e8ee44a",
        "etiquetas": [
            "Inconsistencia"
        ]
    },
    {
        "publicada": 1,
        "numero": 9844,
        "escrutado": true,
        "digitalizado": 1,
        "id_informacion_mesa_corporacion": "0108001011619844",
        "nombre_archivo": "https://elecciones-hnd-publicacion-prod-us-east-1.s3.us-east-1.amazonaws.com/ACTAS/08/0801098440041000.pdf?X-Amz-Algorithm=AWS4-HMAC-SHA256&X-Amz-Credential=AKIATNSYFO5EYDYMH46K%2F20251207%2Fus-east-1%2Fs3%2Faws4_request&X-Amz-Date=20251207T133528Z&X-Amz-Expires=7200&X-Amz-SignedHeaders=host&X-Amz-Signature=16afad4d967bbfc1d7445462be910e0131b8c70eee7052cb4247351c393f9fdc",
        "etiquetas": [
            "Inconsistencia"
        ]
    }
]