[
    {
        "publicada": 1,
        "numero": 7116,
        "escrutado": true,
        "digitalizado": 1,
        "id_informacion_mesa_corporacion": "0106001010307116",
        "nombre_archivo": "https://elecciones-hnd-publicacion-prod-us-east-1.s3.us-east-1.amazonaws.com/E14/06/001/01/030/E14_P01_06_001_001_00_030_7116_2592.pdf?X-Amz-Algorithm=AWS4-HMAC-SHA256&X-Amz-Credential=AKIATNSYFO5EYDYMH46K%2F20251207%2Fus-east-1%2Fs3%2Faws4_request&X-Amz-Date=20251207T003132Z&X-Amz-Expires=7200&X-Amz-SignedHeaders=host&X-Amz-Signature=d395f40f0cb1ec322aab03708b7dbd6001eb272dec4a06cb1815ed1708b2e7c6",
        "etiquetas": [
            "Divulgada Correctamente"
        ]
    },
    {
        "publicada": 1,
        "numero": 7117,
        "escrutado": true,
        "digitalizado": 1,
        "id_informacion_mesa_corporacion": "0106001010307117",
        "nombre_archivo": "https://elecciones-hnd-publicacion-prod-us-east-1.s3.us-east-1.amazonaws.com/E14/06/001/01/030/E14_P01_06_001_001_00_030_7117_2592.pdf?X-Amz-Algorithm=AWS4-HMAC-SHA256&X-Amz-Credential=AKIATNSYFO5EYDYMH46K%2F20251207%2Fus-east-1%2Fs3%2Faws4_request&X-Amz-Date=20251207T003132Z&X-Amz-Expires=7200&X-Amz-SignedHeaders=host&X-Amz-Signature=f11795c7368c94d75c19104921355e874d79f441742305c5f27760b45565f54b",
        "etiquetas": [
            "Divulgada Correctamente"
        ]
    },
    {
        "publicada": 1,
        "numero": 7118,
        "escrutado": true,
        "digitalizado": 1,
        "id_informacion_mesa_corporacion": "0106001010307118",
        "nombre_archivo": "https://elecciones-hnd-publicacion-prod-us-east-1.s3.us-east-1.amazonaws.com/E14/06/001/01/030/E14_P01_06_001_001_00_030_7118_2592.pdf?X-Amz-Algorithm=AWS4-HMAC-SHA256&X-Amz-Credential=AKIATNSYFO5EYDYMH46K%2F20251207%2Fus-east-1%2Fs3%2Faws4_request&X-Amz-Date=20251207T003132Z&X-Amz-Expires=7200&X-Amz-SignedHeaders=host&X-Amz-Signature=d24328f17383d09ce71b48ec0794133ba1f292997425bdef937f8954afdb0016",
        "etiquetas": [
            "Divulgada Correctamente"
        ]
    },
    {
        "publicada": 1,
        "numero": 7119,
        "escrutado": true,
        "digitalizado": 1,
        "id_informacion_mesa_corporacion": "0106001010307119",
        "nombre_archivo": "https://elecciones-hnd-publicacion-prod-us-east-1.s3.us-east-1.amazonaws.com/E14/06/001/01/030/E14_P01_06_001_001_00_030_7119_2593.pdf?X-Amz-Algorithm=AWS4-HMAC-SHA256&X-Amz-Credential=AKIATNSYFO5EYDYMH46K%2F20251207%2Fus-east-1%2Fs3%2Faws4_request&X-Amz-Date=20251207T003132Z&X-Amz-Expires=7200&X-Amz-SignedHeaders=host&X-Amz-Signature=bb51c9a4f1e61b5e91ab8e840f97cd48176034fb1a2a460b28d6fb1911827120",
        "etiquetas": [
            "Divulgada Correctamente"
        ]
    },
    {
        "publicada": 1,
        "numero": 7120,
        "escrutado": true,
        "digitalizado": 1,
        "id_informacion_mesa_corporacion": "0106001010307120",
        "nombre_archivo": "https://elecciones-hnd-publicacion-prod-us-east-1.s3.us-east-1.amazonaws.com/ACTAS/06/0601071200041000.pdf?X-Amz-Algorithm=AWS4-HMAC-SHA256&X-Amz-Credential=AKIATNSYFO5EYDYMH46K%2F20251207%2Fus-east-1%2Fs3%2Faws4_request&X-Amz-Date=20251207T003132Z&X-Amz-Expires=7200&X-Amz-SignedHeaders=host&X-Amz-Signature=d3245c4b5b5336d7ef1b7f7e4e9fa80040069de32ee1ac98cb5e25b4b167b968",
        "etiquetas": [
            "Divulgada Correctamente"
        ]
    },
    {
        "publicada": 1,
        "numero": 7121,
        "escrutado": true,
        "digitalizado": 1,
        "id_informacion_mesa_corporacion": "0106001010307121",
        "nombre_archivo": "https://elecciones-hnd-publicacion-prod-us-east-1.s3.us-east-1.amazonaws.com/ACTAS/06/0601071210041000.pdf?X-Amz-Algorithm=AWS4-HMAC-SHA256&X-Amz-Credential=AKIATNSYFO5EYDYMH46K%2F20251207%2Fus-east-1%2Fs3%2Faws4_request&X-Amz-Date=20251207T003132Z&X-Amz-Expires=7200&X-Amz-SignedHeaders=host&X-Amz-Signature=c22c9e0ce09e68b34b91042a9c3e551e4ed830d403703668cb28084c33ed7392",
        "etiquetas": [
            "Divulgada Correctamente"
        ]
    }
]